ourlib/__init__.py
ourlib/command_line.py
ourlib/ourlib.py
ourlib-0.2.3.dist-info/LICENSE
ourlib-0.2.3.dist-info/METADATA
ourlib-0.2.3.dist-info/WHEEL
ourlib-0.2.3.dist-info/entry_points.txt
ourlib-0.2.3.dist-info/top_level.txt
ourlib-0.2.3.dist-info/RECORD
