Metadata-Version: 2.1
Name: ourlib
Version: 0.2.3
Summary: Python package for ourlib.
Home-page: https://github.com/kunxl-gg/Mercor-pypi
Author: PT
Author-email: name@gmail.com
Classifier: Programming Language :: Python :: 3
Classifier: License :: OSI Approved :: MIT License
Classifier: Operating System :: OS Independent
Requires-Python: >=3.8
License-File: LICENSE
Requires-Dist: torch
Requires-Dist: pandas
Requires-Dist: scikit-learn
